.bandit
.coveralls.yaml
.gitignore
.tool-versions
.travis.yml
CODE_OF_CONDUCT.md
CONTRIBUTING.md
Dockerfile
LICENSE
MANIFEST.in
Makefile
README.md
barterdude.jpg
docker-compose.yml
setup.cfg
setup.py
./barterdude/__init__.py
./barterdude/conf.py
./barterdude/message.py
./barterdude/mocks.py
./barterdude/monitor.py
./barterdude/hooks/__init__.py
./barterdude/hooks/healthcheck.py
./barterdude/hooks/logging.py
./barterdude/hooks/metrics/__init__.py
./barterdude/hooks/metrics/prometheus/__init__.py
./barterdude/hooks/metrics/prometheus/definitions.py
./barterdude/hooks/metrics/prometheus/metrics.py
./requirements/requirements_base.txt
./requirements/requirements_test.txt
.github/workflows/blackbox-workflow.yml
.github/workflows/codeql-analysis.yml
.github/workflows/main.yml
barterdude/__init__.py
barterdude/conf.py
barterdude/message.py
barterdude/mocks.py
barterdude/monitor.py
barterdude.egg-info/PKG-INFO
barterdude.egg-info/SOURCES.txt
barterdude.egg-info/dependency_links.txt
barterdude.egg-info/requires.txt
barterdude.egg-info/top_level.txt
barterdude/hooks/__init__.py
barterdude/hooks/healthcheck.py
barterdude/hooks/logging.py
barterdude/hooks/metrics/__init__.py
barterdude/hooks/metrics/prometheus/__init__.py
barterdude/hooks/metrics/prometheus/definitions.py
barterdude/hooks/metrics/prometheus/metrics.py
requirements/requirements_base.txt
requirements/requirements_test.txt