Metadata-Version: 2.1
Name: barterdude
Version: 1.3.2
Summary: Message exchange engine to build pipelines using brokers like RabbitMQ
Home-page: https://github.com/olxbr/BarterDude/
Download-URL: https://github.com/olxbr/BarterDude/archive/master.zip
Author: Olx
License: Apache 2
Classifier: Programming Language :: Python :: 3.9
Classifier: Programming Language :: Python :: 3.10
Classifier: Programming Language :: Python :: 3.11
Classifier: License :: OSI Approved :: Apache Software License
Classifier: Topic :: Software Development :: Libraries :: Python Modules
Classifier: Topic :: Software Development :: Libraries :: Application Frameworks
License-File: LICENSE
Requires-Dist: async-worker==0.20.0
Requires-Dist: python-json-logger==2.0.1
Requires-Dist: jsonschema==3.2.0
Provides-Extra: all
